{
  "last_updated": "2025-01-08 18:20:40 MST",
  "cars": [
    {
      "title": "2019 Audi A4 2.0T quattro Premium Plus",
      "details": "115,294 Miles Automatic AWD 2.0L I-4",
      "bid_price": "$13,900",
      "bin_price": "$19,000",
      "bid_end_date": "1/15/25 9:00 AM",
      "image": "https://repos.americafirst.com/storage/images/unit-pictures/677c7499e588b.jpeg",
      "url": "https://repos.americafirst.com/units/2663",
      "source": "AFCU"
    },
    {
      "title": "2022 Audi Q3 quattro S line Premium 45 TFSI",
      "details": "35,123 Miles Automatic AWD 2.0L I-4",
      "bid_price": "$24,000",
      "bin_price": "$27,900",
      "bid_end_date": "1/15/25 9:00 AM",
      "image": "https://repos.americafirst.com/storage/images/unit-pictures/674603e7a5236.jpeg",
      "url": "https://repos.americafirst.com/units/2602",
      "source": "AFCU"
    },
    {
      "title": "2019 Ford F-250 Super Duty XLT",
      "details": "80,709 Miles Automatic 4X4 6.2L V-8",
      "bid_price": "$28,005",
      "bin_price": "$34,000",
      "bid_end_date": "1/15/25 9:00 AM",
      "image": "https://repos.americafirst.com/storage/images/unit-pictures/677c79bc35863.jpeg",
      "url": "https://repos.americafirst.com/units/2664",
      "source": "AFCU"
    },
    {
      "title": "2019 Ford Fiesta S",
      "details": "51,057 Miles Manual FWD 1.6L I-4",
      "bid_price": "$7,000",
      "bin_price": "$9,200",
      "bid_end_date": "1/15/25 9:00 AM",
      "image": "https://repos.americafirst.com/storage/images/unit-pictures/677c6a6ec2ee9.jpeg",
      "url": "https://repos.americafirst.com/units/2660",
      "source": "AFCU"
    },
    {
      "title": "2019 Ford Ranger XLT",
      "details": "78,261 Miles Automatic 4X4 2.3L I-4",
      "bid_price": "$22,000",
      "bin_price": "$26,400",
      "bid_end_date": "1/15/25 9:00 AM",
      "image": "https://repos.americafirst.com/storage/images/unit-pictures/677c7f240b812.jpeg",
      "url": "https://repos.americafirst.com/units/2665",
      "source": "AFCU"
    },
    {
      "title": "2021 GMC Sierra 1500 Denali",
      "details": "81,269 Miles Automatic 4X4 3.0L I-6",
      "bid_price": "$38,500",
      "bin_price": "$45,000",
      "bid_end_date": "1/15/25 9:00 AM",
      "image": "https://repos.americafirst.com/storage/images/unit-pictures/677c8319392a2.jpeg",
      "url": "https://repos.americafirst.com/units/2666",
      "source": "AFCU"
    },
    {
      "title": "2018 GMC Sierra 1500 SLT",
      "details": "108,495 Miles Automatic 4X4 6.2L V-8",
      "bid_price": "$25,900",
      "bin_price": "$32,100",
      "bid_end_date": "1/15/25 9:00 AM",
      "image": "https://repos.americafirst.com/storage/images/unit-pictures/677c70c1e16b0.jpeg",
      "url": "https://repos.americafirst.com/units/2662",
      "source": "AFCU"
    },
    {
      "title": "2022 Jeep Gladiator Mojave",
      "details": "42,300 Miles Automatic 4X4 3.6L V-6",
      "bid_price": "$36,500",
      "bin_price": "$41,900",
      "bid_end_date": "1/15/25 9:00 AM",
      "image": "https://repos.americafirst.com/storage/images/unit-pictures/677c64e21c10e.jpeg",
      "url": "https://repos.americafirst.com/units/2659",
      "source": "AFCU"
    },
    {
      "title": "2022 Kia Seltos SX",
      "details": "12,739 Miles Automatic AWD 1.6L I-4",
      "bid_price": "$22,200",
      "bin_price": "$24,000",
      "bid_end_date": "1/15/25 9:00 AM",
      "image": "https://repos.americafirst.com/storage/images/unit-pictures/677c862f133c5.jpeg",
      "url": "https://repos.americafirst.com/units/2667",
      "source": "AFCU"
    },
    {
      "title": "2017 Nissan Rogue SV",
      "details": "101,108 Miles CVT AWD 2.5L I-4",
      "bid_price": "$7,200",
      "bin_price": "$10,500",
      "bid_end_date": "1/15/25 9:00 AM",
      "image": "https://repos.americafirst.com/storage/images/unit-pictures/674dedaec5050.jpeg",
      "url": "https://repos.americafirst.com/units/2608",
      "source": "AFCU"
    },
    {
      "title": "2022 Subaru Ascent Limited 8-Passenger",
      "details": "27,482 Miles CVT AWD 2.4L H-4",
      "bid_price": "$28,500",
      "bin_price": "$31,200",
      "bid_end_date": "1/15/25 9:00 AM",
      "image": "https://repos.americafirst.com/storage/images/unit-pictures/677c6d4b603a9.jpeg",
      "url": "https://repos.americafirst.com/units/2661",
      "source": "AFCU"
    }
  ]
}