{
    "last_updated": "2023-04-12 19:08:06 MDT",
    "cars": [
        {
            "title": "2011 Chevrolet Camaro SS",
            "details": "77,104 Miles Automatic RWD 6.2L V-8",
            "bid_price": "$16,501",
            "bin_price": "",
            "bid_end_date": "4/19/23 9:00 AM",
            "image": "https://repos.americafirst.com/storage/images/unit-pictures/642f322c7bf7c.jpeg",
            "url": "https://repos.americafirst.com/units/1896",
            "source": "AFCU"
        },
        {
            "title": "2016 Chevrolet Sonic LTZ Auto",
            "details": "115,323 Miles Automatic FWD 1.4L I-4",
            "bid_price": "$6,651",
            "bin_price": "$7,380",
            "bid_end_date": "4/19/23 9:00 AM",
            "image": "https://repos.americafirst.com/storage/images/unit-pictures/642f302073ed3.jpeg",
            "url": "https://repos.americafirst.com/units/1895",
            "source": "AFCU"
        },
        {
            "title": "2018 Ducati Panigale V4 Speciale",
            "details": "2,649 Miles 1,103cc",
            "bid_price": "$22,575",
            "bin_price": "$28,900",
            "bid_end_date": "4/19/23 9:00 AM",
            "image": "https://repos.americafirst.com/storage/images/unit-pictures/642f3364c9860.jpeg",
            "url": "https://repos.americafirst.com/units/1897",
            "source": "AFCU"
        },
        {
            "title": "2016 Ford Fusion SE",
            "details": "76,979 Miles Automatic FWD 2.5L I-4",
            "bid_price": "$10,101",
            "bin_price": "$13,200",
            "bid_end_date": "4/19/23 9:00 AM",
            "image": "https://repos.americafirst.com/storage/images/unit-pictures/642f37bcdeb00.jpeg",
            "url": "https://repos.americafirst.com/units/1899",
            "source": "AFCU"
        },
        {
            "title": "2017 Hyundai SANTA FE Sport 2.4L",
            "details": "79,128 Miles Automatic AWD 2.4L I-4",
            "bid_price": "$14,001",
            "bin_price": "",
            "bid_end_date": "4/19/23 9:00 AM",
            "image": "https://repos.americafirst.com/storage/images/unit-pictures/642f2ed7421b3.jpeg",
            "url": "https://repos.americafirst.com/units/1894",
            "source": "AFCU"
        },
        {
            "title": "2015 Jeep Renegade Front Wheel Drive Sport",
            "details": "90,350 Miles Automatic FWD 2.4L I-4",
            "bid_price": "$10,602",
            "bin_price": "",
            "bid_end_date": "4/19/23 9:00 AM",
            "image": "https://repos.americafirst.com/storage/images/unit-pictures/642f2c23b8e05.jpeg",
            "url": "https://repos.americafirst.com/units/1892",
            "source": "AFCU"
        },
        {
            "title": "2017 Nissan Frontier 2 Wheel Drive SV",
            "details": "98,820 Miles Automatic 4X2 4.0L V-6",
            "bid_price": "$15,800",
            "bin_price": "$16,600",
            "bid_end_date": "4/19/23 9:00 AM",
            "image": "https://repos.americafirst.com/storage/images/unit-pictures/641ca4243e219.jpeg",
            "url": "https://repos.americafirst.com/units/1881",
            "source": "AFCU"
        },
        {
            "title": "2013 Volkswagen Jetta TDI",
            "details": "107,869 Miles Manual FWD 2.0L I-4",
            "bid_price": "$6,805",
            "bin_price": "$9,450",
            "bid_end_date": "4/19/23 9:00 AM",
            "image": "https://repos.americafirst.com/storage/images/unit-pictures/642f2d7d79484.jpeg",
            "url": "https://repos.americafirst.com/units/1893",
            "source": "AFCU"
        }
    ]
}