{
    "last_updated": "2022-06-29 09:51:47 MDT",
    "cars": [
        {
            "title": "2016 Dodge Challenger R/T Scat Pack",
            "details": "35,319 Miles Automatic RWD 6.4L V-8",
            "bid_price": "",
            "bin_price": "$36,780",
            "bid_end_date": "7/6/22 9:00 AM",
            "image": "https://repos.americafirst.com/storage/images/unit-pictures/62b4cfc822e0e.jpeg",
            "url": "https://repos.americafirst.com/units/1652",
            "source": "AFCU"
        },
        {
            "title": "2008 Dodge Ram Pickup 1500 SLT",
            "details": "111,252 Miles Automatic 4WD 4.7L V-8",
            "bid_price": "",
            "bin_price": "$14,595",
            "bid_end_date": "7/6/22 9:00 AM",
            "image": "https://repos.americafirst.com/storage/images/unit-pictures/62b4df284181f.jpeg",
            "url": "https://repos.americafirst.com/units/1654",
            "source": "AFCU"
        },
        {
            "title": "2007 FOREST  RIVER  WILDERNESS M-27OFQ",
            "details": "",
            "bid_price": "$10,700",
            "bin_price": "",
            "bid_end_date": "7/6/22 9:00 AM",
            "image": "https://repos.americafirst.com/storage/images/unit-pictures/62b9fc981bd08.jpeg",
            "url": "https://repos.americafirst.com/units/1659",
            "source": "AFCU"
        },
        {
            "title": "2011 GMC Sierra 1500 SLE",
            "details": "129,975 Miles Automatic 4X2 4.8L V-8",
            "bid_price": "",
            "bin_price": "$16,430",
            "bid_end_date": "7/6/22 9:00 AM",
            "image": "https://repos.americafirst.com/storage/images/unit-pictures/62b61573ad0cd.jpeg",
            "url": "https://repos.americafirst.com/units/1656",
            "source": "AFCU"
        },
        {
            "title": "2019 Kia Soul +",
            "details": "91,646 Miles Automatic FWD 2.0L I-4",
            "bid_price": "",
            "bin_price": "$17,490",
            "bid_end_date": "7/6/22 9:00 AM",
            "image": "https://repos.americafirst.com/storage/images/unit-pictures/62b62dde39f0c.jpeg",
            "url": "https://repos.americafirst.com/units/1657",
            "source": "AFCU"
        },
        {
            "title": "2018 Nissan Altima 2.5 SV",
            "details": "70,393 Miles CVT FWD 2.5L I-4",
            "bid_price": "",
            "bin_price": "$19,600",
            "bid_end_date": "7/6/22 9:00 AM",
            "image": "https://repos.americafirst.com/storage/images/unit-pictures/628e9c5806e4b.jpeg",
            "url": "https://repos.americafirst.com/units/1620",
            "source": "AFCU"
        },
        {
            "title": "2019 Nissan Armada SL",
            "details": "66,889 Miles Automatic 4X4 5.6L V-8",
            "bid_price": "$35,975",
            "bin_price": "$39,679",
            "bid_end_date": "7/6/22 9:00 AM",
            "image": "https://repos.americafirst.com/storage/images/unit-pictures/62b60fa3041da.jpeg",
            "url": "https://repos.americafirst.com/units/1655",
            "source": "AFCU"
        },
        {
            "title": "2019 Nissan Sentra",
            "details": "72,593 Miles CVT FWD 1.8L I-4",
            "bid_price": "",
            "bin_price": "$17,690",
            "bid_end_date": "7/6/22 9:00 AM",
            "image": "https://repos.americafirst.com/storage/images/unit-pictures/62b9cf9f1d1d2.jpeg",
            "url": "https://repos.americafirst.com/units/1658",
            "source": "AFCU"
        }
    ]
}