{
    "last_updated": "2022-11-30 18:39:32 MST",
    "cars": [
        {
            "title": "2014 Buick Enclave Leather",
            "details": "146,271 Miles Automatic AWD 3.6L V-6",
            "bid_price": "",
            "bin_price": "$11,175",
            "bid_end_date": "12/7/22 9:00 AM",
            "image": "https://repos.americafirst.com/storage/images/unit-pictures/636986c86c422.jpeg",
            "url": "https://repos.americafirst.com/units/1764",
            "source": "AFCU"
        },
        {
            "title": "2015 Chrysler 200 C",
            "details": "101,802 Miles Automatic FWD 2.4L I-4",
            "bid_price": "$7,750",
            "bin_price": "$11,130",
            "bid_end_date": "12/7/22 9:00 AM",
            "image": "https://repos.americafirst.com/storage/images/unit-pictures/63406af9b83b7.jpeg",
            "url": "https://repos.americafirst.com/units/1744",
            "source": "AFCU"
        },
        {
            "title": "2019 Dodge Charger SRT Hellcat",
            "details": "43,191 Miles Automatic RWD 6.2L V-8",
            "bid_price": "$48,900",
            "bin_price": "$53,200",
            "bid_end_date": "12/7/22 9:00 AM",
            "image": "https://repos.americafirst.com/storage/images/unit-pictures/63695347285ff.jpeg",
            "url": "https://repos.americafirst.com/units/1759",
            "source": "AFCU"
        },
        {
            "title": "2018 Dodge Charger GT",
            "details": "45,243 Miles Automatic AWD 3.6L V-6",
            "bid_price": "",
            "bin_price": "$28,000",
            "bid_end_date": "12/7/22 9:00 AM",
            "image": "https://repos.americafirst.com/storage/images/unit-pictures/6376c35679df3.jpeg",
            "url": "https://repos.americafirst.com/units/1774",
            "source": "AFCU"
        },
        {
            "title": "2016 Ford Escape SE",
            "details": "81,874 Miles Automatic AWD 2.0L I-4",
            "bid_price": "",
            "bin_price": "$14,900",
            "bid_end_date": "12/7/22 9:00 AM",
            "image": "https://repos.americafirst.com/storage/images/unit-pictures/638126d984dd9.jpeg",
            "url": "https://repos.americafirst.com/units/1780",
            "source": "AFCU"
        },
        {
            "title": "2015 Ford Focus ST",
            "details": "52,994 Miles Manual FWD 2.0L I-4",
            "bid_price": "",
            "bin_price": "$16,600",
            "bid_end_date": "12/7/22 9:00 AM",
            "image": "https://repos.americafirst.com/storage/images/unit-pictures/638123434f260.jpeg",
            "url": "https://repos.americafirst.com/units/1779",
            "source": "AFCU"
        },
        {
            "title": "2011 Harley-Davidson Dyna Glide Wide Glide",
            "details": "27,351 Miles 1,584cc",
            "bid_price": "",
            "bin_price": "$9,600",
            "bid_end_date": "12/7/22 9:00 AM",
            "image": "https://repos.americafirst.com/storage/images/unit-pictures/63814f1b4ac80.jpeg",
            "url": "https://repos.americafirst.com/units/1784",
            "source": "AFCU"
        },
        {
            "title": "2018 Hyundai ELANTRA SEL",
            "details": "73,915 Miles Automatic FWD 2.0L I-4",
            "bid_price": "$12,750",
            "bin_price": "$15,980",
            "bid_end_date": "12/7/22 9:00 AM",
            "image": "https://repos.americafirst.com/storage/images/unit-pictures/63812abdb3267.jpeg",
            "url": "https://repos.americafirst.com/units/1781",
            "source": "AFCU"
        },
        {
            "title": "2013 INFINITI QX56 Base",
            "details": "125,142 Miles Automatic 4X4 5.6L V-8",
            "bid_price": "$14,301",
            "bin_price": "$16,550",
            "bid_end_date": "12/7/22 9:00 AM",
            "image": "https://repos.americafirst.com/storage/images/unit-pictures/636957743026a.jpeg",
            "url": "https://repos.americafirst.com/units/1760",
            "source": "AFCU"
        },
        {
            "title": "2016 Kia Sorento EX V6",
            "details": "128,533 Miles Automatic AWD 3.3L V-6",
            "bid_price": "",
            "bin_price": "$13,870",
            "bid_end_date": "12/7/22 9:00 AM",
            "image": "https://repos.americafirst.com/storage/images/unit-pictures/638114cf12abb.jpeg",
            "url": "https://repos.americafirst.com/units/1777",
            "source": "AFCU"
        },
        {
            "title": "2013 Land Rover Range Rover Sport Autobiography",
            "details": "123,825 Miles Automatic 4X4 5.0L V-8",
            "bid_price": "$17,050",
            "bin_price": "$22,400",
            "bid_end_date": "12/7/22 9:00 AM",
            "image": "https://repos.americafirst.com/storage/images/unit-pictures/6322141b69fea.jpeg",
            "url": "https://repos.americafirst.com/units/1714",
            "source": "AFCU"
        },
        {
            "title": "2017 Nissan Rogue S",
            "details": "88,663 Miles CVT AWD 2.5L I-4",
            "bid_price": "$12,725",
            "bin_price": "$16,475",
            "bid_end_date": "12/7/22 9:00 AM",
            "image": "https://repos.americafirst.com/storage/images/unit-pictures/63813a2909c05.jpeg",
            "url": "https://repos.americafirst.com/units/1782",
            "source": "AFCU"
        },
        {
            "title": "2015 Toyota Camry SE",
            "details": "104,543 Miles Automatic FWD 2.5L I-4",
            "bid_price": "$11,300",
            "bin_price": "$13,175",
            "bid_end_date": "12/7/22 9:00 AM",
            "image": "https://repos.americafirst.com/storage/images/unit-pictures/6351658eea892.jpeg",
            "url": "https://repos.americafirst.com/units/1751",
            "source": "AFCU"
        },
        {
            "title": "2017 Toyota Corolla SE",
            "details": "94,236 Miles CVT FWD 1.8L I-4",
            "bid_price": "$11,650",
            "bin_price": "$15,000",
            "bid_end_date": "12/7/22 9:00 AM",
            "image": "https://repos.americafirst.com/storage/images/unit-pictures/6273fe1573c13.jpeg",
            "url": "https://repos.americafirst.com/units/1602",
            "source": "AFCU"
        },
        {
            "title": "2016 Toyota Highlander Limited Platinum",
            "details": "97,048 Miles Automatic AWD 3.5L V-6",
            "bid_price": "$23,781",
            "bin_price": "",
            "bid_end_date": "12/7/22 9:00 AM",
            "image": "https://repos.americafirst.com/storage/images/unit-pictures/63811b025417d.jpeg",
            "url": "https://repos.americafirst.com/units/1778",
            "source": "AFCU"
        },
        {
            "title": "2015 YAMAHA XV250F",
            "details": "3,273 Miles 249cc",
            "bid_price": "$2,154",
            "bin_price": "$2,980",
            "bid_end_date": "12/7/22 9:00 AM",
            "image": "https://repos.americafirst.com/storage/images/unit-pictures/63814b36afa03.jpeg",
            "url": "https://repos.americafirst.com/units/1783",
            "source": "AFCU"
        }
    ]
}